qmenuview/__init__.py
qmenuview/view.py
qmenuview-0.1.4.dist-info/top_level.txt
qmenuview-0.1.4.dist-info/METADATA
qmenuview-0.1.4.dist-info/DESCRIPTION.rst
qmenuview-0.1.4.dist-info/metadata.json
qmenuview-0.1.4.dist-info/WHEEL
qmenuview-0.1.4.dist-info/RECORD
