Metadata-Version: 2.0
Name: qmenuview
Version: 0.1.4
Summary: PySide view for menues
Home-page: https://github.com/storax/qmenuview
Author: David Zuber
Author-email: zuber.david@gmx.de
License: BSD
Keywords: qmenuview
Platform: UNKNOWN
Classifier: Development Status :: 2 - Pre-Alpha
Classifier: Intended Audience :: Developers
Classifier: License :: OSI Approved :: BSD License
Classifier: Natural Language :: English
Classifier: Programming Language :: Python :: 2.7
Requires-Dist: PySide
